site_scrapers/__init__.py
site_scrapers/models/Car.py
site_scrapers/models/__init__.py
site_scrapers/models/py.typed
site_scrapers/scrapers/__init__.py
site_scrapers/scrapers/details/__init__.py
site_scrapers/scrapers/details/brcAuto.py
site_scrapers/scrapers/details/inchcape.py
site_scrapers/scrapers/details/mollerAuto.py
site_scrapers/scrapers/details/py.typed
site_scrapers/scrapers/list/__init__.py
site_scrapers/scrapers/list/brcAuto.py
site_scrapers/scrapers/list/inchcape.py
site_scrapers/scrapers/list/mollerAuto.py
site_scrapers/scrapers/list/py.typed
site_scrapers/scrapers/py.typed
site_scrapers/scrapers/scraper.py
site_scrapers/scrapers/utils.py
site_scrapers/tests/__init__.py
site_scrapers/tests/scrapers/__init__.py
site_scrapers/tests/scrapers/details/__init__.py
site_scrapers/tests/scrapers/details/brc_data/brc_bmw_220.html
site_scrapers/tests/scrapers/details/brc_data/brc_ford_focus.html
site_scrapers/tests/scrapers/details/brc_data/brc_mercedes_gl-3.0.html
site_scrapers/tests/scrapers/details/brc_data/brc_mercedes_ml_500.html
site_scrapers/tests/scrapers/details/inchcape/inchcape_bmw_530.html
site_scrapers/tests/scrapers/details/inchcape/inchcape_bmw_x6m.html
site_scrapers/tests/scrapers/details/inchcape/inchcape_ford_mondeo.html
site_scrapers/tests/scrapers/details/inchcape/inchcape_lexus_ux.html
site_scrapers/tests/scrapers/details/inchcape/inchcape_vw_tiguan.html
site_scrapers/tests/scrapers/details/moller_data/moller_audi.html
site_scrapers/tests/scrapers/details/moller_data/moller_audi_a6_sport.html
site_scrapers/tests/scrapers/details/moller_data/moller_vw_amarok.html
site_scrapers/tests/scrapers/details/test_brcAuto.py
site_scrapers/tests/scrapers/details/test_inchcape.py
site_scrapers/tests/scrapers/details/test_mollerAuto.py
site_scrapers/tests/scrapers/test_utils.py
site_scrapers/utils/__init__.py
site_scrapers/utils/sync_to_async.py
site_scrapers-0.0.34.dist-info/WHEEL
site_scrapers-0.0.34.dist-info/METADATA
site_scrapers-0.0.34.dist-info/RECORD
